odoo/addons/account_analytic_root/README.rst
odoo/addons/account_analytic_root/__init__.py
odoo/addons/account_analytic_root/__manifest__.py
odoo/addons/account_analytic_root/i18n/account_analytic_root.pot
odoo/addons/account_analytic_root/i18n/eu_ES.po
odoo/addons/account_analytic_root/i18n/it.po
odoo/addons/account_analytic_root/models/__init__.py
odoo/addons/account_analytic_root/models/account_analytic_account.py
odoo/addons/account_analytic_root/readme/DESCRIPTION.rst
odoo/addons/account_analytic_root/static/description/icon.png
odoo/addons/account_analytic_root/static/description/index.html
odoo/addons/account_analytic_root/tests/__init__.py
odoo/addons/account_analytic_root/tests/test_account_analytic.py
odoo_addon_account_analytic_root-16.0.1.0.0.5.dist-info/METADATA
odoo_addon_account_analytic_root-16.0.1.0.0.5.dist-info/WHEEL
odoo_addon_account_analytic_root-16.0.1.0.0.5.dist-info/top_level.txt
odoo_addon_account_analytic_root-16.0.1.0.0.5.dist-info/RECORD
